LICENSE.txt
MANIFEST.in
README.rst
setup.py
imperituroard/__init__.py
imperituroard/core.py
imperituroard.egg-info/PKG-INFO
imperituroard.egg-info/SOURCES.txt
imperituroard.egg-info/dependency_links.txt
imperituroard.egg-info/not-zip-safe
imperituroard.egg-info/requires.txt
imperituroard.egg-info/top_level.txt
imperituroard/projects/dns/__init__.py
imperituroard/projects/dns/functions.py
imperituroard/projects/dns/influxdb.py
imperituroard/projects/freewifi/__init__.py
imperituroard/projects/freewifi/mikrotik.py
imperituroard/projects/messagehub/__init__.py
imperituroard/projects/messagehub/get_stat.py
imperituroard/universal/__init__.py
imperituroard/universal/influxdbdata.py