Metadata-Version: 1.1
Name: imperituroard
Version: 0.9
Summary: Procedures from imperituroard
Home-page: UNKNOWN
Author: Dzmitry Buynovskiy
Author-email: imperituro@mail.com
License: MIT
Keywords: monitoring additional procedures
Platform: UNKNOWN
Classifier: Development Status :: 3 - Alpha
Classifier: License :: OSI Approved :: MIT License
Classifier: Programming Language :: Python :: 3.7
Classifier: Topic :: Text Processing :: Linguistic
